modern_greek_accentuation/__init__.py
modern_greek_accentuation/_helpers.py
modern_greek_accentuation/_version.py
modern_greek_accentuation/accentuation.py
modern_greek_accentuation/augmentify.py
modern_greek_accentuation/resources.py
modern_greek_accentuation/syllabify.py
modern_greek_accentuation/transcription.py
modern_greek_accentuation-1.0.7.dist-info/AUTHORS
modern_greek_accentuation-1.0.7.dist-info/LICENSE
modern_greek_accentuation-1.0.7.dist-info/METADATA
modern_greek_accentuation-1.0.7.dist-info/WHEEL
modern_greek_accentuation-1.0.7.dist-info/top_level.txt
modern_greek_accentuation-1.0.7.dist-info/RECORD
