Metadata-Version: 2.1
Name: modern-greek-accentuation
Version: 1.0.7
Summary: Python 3 library for accenting, analyzing accentuation, syllabification, augmentation and transcription of Modern Greek words",
Home-page: https://github.com/PicusZeus/modern-greek-accentuation
Author: Krzysztof H
Author-email: krzysztof.hilman@gmail.com
License: MIT
Platform: any
Classifier: Development Status :: 4 - Beta
Classifier: License :: OSI Approved :: MIT License
Classifier: Operating System :: OS Independent
Classifier: Programming Language :: Python :: 3
Classifier: Programming Language :: Python :: 3 :: Only
Classifier: Programming Language :: Python :: 3.6
Classifier: Programming Language :: Python :: 3.7
Classifier: Programming Language :: Python :: 3.8
Classifier: Programming Language :: Python :: 3.9
Classifier: Topic :: Software Development :: Libraries :: Python Modules
Requires-Python: >=3.1
License-File: LICENSE
License-File: AUTHORS
